react_select/ReactSelect.py
react_select/__init__.py
selenium_react_select-0.0.4.dist-info/LICENSE.txt
selenium_react_select-0.0.4.dist-info/METADATA
selenium_react_select-0.0.4.dist-info/WHEEL
selenium_react_select-0.0.4.dist-info/top_level.txt
selenium_react_select-0.0.4.dist-info/RECORD
