Metadata-Version: 2.1
Name: selenium-react-select
Version: 0.0.4
Summary: package for react select : version 1 and 2
Home-page: https://github.com/karins28/selenium-react-select
Author: Karin Shaim
Author-email: karins1010@gmail.com
License: UNKNOWN
Platform: UNKNOWN
Classifier: Programming Language :: Python :: 2.7
Classifier: License :: OSI Approved :: MIT License
Classifier: Operating System :: OS Independent
Requires-Dist: selenium
